<?xml version="1.0" encoding="UTF-8"?>

<Defs>
    <ResearchProjectDef>
        <defName>RATS_RATS</defName>
        <label>R.A.T.S.</label>
        <description>Rimtech Assisted Targeting System</description>
        <baseCost>2000</baseCost>
        <techLevel>Industrial</techLevel>
        <prerequisites>
            <li>AdvancedFabrication</li>
            <li>Gunlink</li>
        </prerequisites>
        <requiredResearchFacilities>
            <li>MultiAnalyzer</li>
        </requiredResearchFacilities>
        <requiredResearchBuilding>HiTechResearchBench</requiredResearchBuilding>
        <researchViewX>17.00</researchViewX>
        <researchViewY>5.4</researchViewY>
    </ResearchProjectDef>
</Defs>